roscenes/__init__.py
roscenes/consts.py
roscenes/misc.py
roscenes/transform.py
roscenes/typing.py
roscenes/data/__init__.py
roscenes/data/camera.py
roscenes/data/clip.py
roscenes/data/frame.py
roscenes/data/metadata.py
roscenes/data/scene.py
roscenes/evaluation/__init__.py
roscenes/evaluation/detection/__init__.py
roscenes/evaluation/detection/__main__.py
roscenes/evaluation/detection/aggregator.py
roscenes/evaluation/detection/config.py
roscenes/evaluation/detection/evaluator.py
roscenes/evaluation/detection/handlers.py
roscenes/evaluation/detection/prediction.py
roscenes/evaluation/detection/result.py
roscenes/visualizer/__init__.py
roscenes/visualizer/__main__.py
roscenes-0.0.1.dist-info/LICENSE
roscenes-0.0.1.dist-info/METADATA
roscenes-0.0.1.dist-info/WHEEL
roscenes-0.0.1.dist-info/top_level.txt
roscenes-0.0.1.dist-info/RECORD
