Metadata-Version: 2.1
Name: roscenes
Version: 0.0.1
Summary: RoScenes dataset devkit
Author-email: Xiaosu Zhu <zhuxiaosu.zxs@alibaba-inc.com>
License: Apache 2.0
Classifier: Development Status :: 3 - Alpha
Classifier: Programming Language :: Python
Requires-Python: >=3.10
License-File: LICENSE
Requires-Dist: lmdb <2
Requires-Dist: packaging
Requires-Dist: numpy <2
Requires-Dist: shapely <3
Requires-Dist: dashtable <2
Requires-Dist: rich <14
Requires-Dist: scipy <2
Requires-Dist: click <9
Requires-Dist: joblib <2
Requires-Dist: pyyaml <7
Requires-Dist: opencv-python-headless <5
Requires-Dist: matplotlib <4
Requires-Dist: bs4 <0.1
Requires-Dist: seaborn <1
